geoVeRoPy/__init__.py
geoVeRoPy/animation.py
geoVeRoPy/bnbTree.py
geoVeRoPy/cetsp.py
geoVeRoPy/color.py
geoVeRoPy/common.py
geoVeRoPy/curveArc.py
geoVeRoPy/geometry.py
geoVeRoPy/grid.py
geoVeRoPy/gridSurface.py
geoVeRoPy/instance.py
geoVeRoPy/msg.py
geoVeRoPy/obj2Obj.py
geoVeRoPy/op.py
geoVeRoPy/plot.py
geoVeRoPy/polyTour.py
geoVeRoPy/province.py
geoVeRoPy/ring.py
geoVeRoPy/road.py
geoVeRoPy/travel.py
geoVeRoPy/tree.py
geoVeRoPy/tsp.py
geoveropy-0.0.20.dist-info/licenses/LICENSE
geoveropy-0.0.20.dist-info/METADATA
geoveropy-0.0.20.dist-info/WHEEL
geoveropy-0.0.20.dist-info/top_level.txt
geoveropy-0.0.20.dist-info/RECORD
