Metadata-Version: 2.4
Name: geoVeRoPy
Version: 0.0.20
Summary: geoVeRoPy: Geometrical Vehicle Routing Problem solved by Python
Author-email: Lan Peng <lanpeng@shu.edu.cn>
License-Expression: MIT
Project-URL: Homepage, https://github.com/isaac0821/geoVeRoPy/
Project-URL: Issues, https://github.com/isaac0821/geoVeRoPy/issues
Project-URL: Documentation, https://isaac0821.github.io/geoVeRoPy/
Classifier: Development Status :: 2 - Pre-Alpha
Classifier: Programming Language :: Python :: 3
Classifier: Operating System :: OS Independent
Requires-Python: >=3.11
License-File: LICENSE
Requires-Dist: numpy
Requires-Dist: scipy
Requires-Dist: geopy
Requires-Dist: geojson
Requires-Dist: matplotlib
Requires-Dist: shapely
Requires-Dist: networkx
Dynamic: license-file
